archsnap/__init__.py
archsnap/__main__.py
archsnap/config.py
archsnap/main.py
archsnap/data/artefact_scene.blend
archsnap/data/icos/icon.ico
archsnap/data/textures/scale.png
archsnap/gui/__init__.py
archsnap/gui/init_gui.py
archsnap/mesh/__init__.py
archsnap/mesh/mesh.py
archsnap-0.1.2.dist-info/licenses/LICENSE
archsnap-0.1.2.dist-info/METADATA
archsnap-0.1.2.dist-info/WHEEL
archsnap-0.1.2.dist-info/top_level.txt
archsnap-0.1.2.dist-info/RECORD
