Metadata-Version: 2.4
Name: archSnap
Version: 0.1.2
Summary: A package for the archSnap visualisation generator
Author: Jordy Didier Orellana Figueroa
License-Expression: GPL-3.0-or-later
Project-URL: Repository, https://github.com/ac-jorellanaf/archSnap
Classifier: Programming Language :: Python :: 3.11
Classifier: Development Status :: 4 - Beta
Classifier: Operating System :: OS Independent
Classifier: Topic :: Multimedia :: Graphics :: 3D Rendering
Requires-Python: >=3.11.0
License-File: LICENSE
Requires-Dist: bpy>=4.4.0
Dynamic: license-file
